{
    "screen_desc": "It seems you haven't uploaded a screenshot yet. Could you try uploading the image again? I'd be happy to assist!",
    "action_think": "The user has searched for 'good Indian restaurants' in the Google Chrome browser and navigated through the search results. Now, they are likely looking for more specific restaurant details or actions such as making a reservation or calling. The current screen displays multiple restaurant options with actionable buttons. The next step would be to select a specific restaurant or perform an action related to a restaurant of interest.",
    "action_plan": [
        "Click on the 'Hyderabad Dum Biryani' restaurant to view more details."
    ],
    "relevant_ui_path": null,
    "action_desc": "Click on the 'Hyderabad Dum Biryani' restaurant to view more details.",
    "action_result": "The execution of user request is stopped.",
    "prev_action_result": "By clicking on the \"More places\" button, the screen now shows additional options or a list of places that could include more Indian restaurants. This action is a step towards fulfilling the user request to search for good Indian restaurants because it expands the selection of available places, potentially helping to find more options. Therefore, this action has made progress towards the user\u2019s goal of locating good Indian restaurants.",
    "action_predict": {
        "COAT": {
            "tag": {
                "ACTION": "click_element",
                "ARGS": {
                    "idx": 13
                }
            }
        }
    }
}