{"user_request": "uninstall \"Lyft - Rideshare, Bikes, Scooters & Transit\"", "image_path": "/root/GUI-Memory/data/android_in_the_zoo/test_sample/install/INSTALL-689623307793919007/INSTALL-689623307793919007_2.png", "screen_desc": "It seems there was an issue with the screenshot. Could you try uploading it again?", "history_actions": ["press the home button", "scroll up"], "think_action": {"Thought": "The user wants to uninstall the 'Lyft' app, but the app is not visible on the current screen. I'll need to navigate through the 'All apps' section or search for the app to proceed with uninstallation.", "Future Action Plan": ["Search for 'Lyft' using the search bar at the top of the screen.", "If the app appears in the search results, tap on it to access the app options.", "Select 'Uninstall' to remove the app."], "Next Single Step Action": "Use the search bar at the top of the screen to search for 'Lyft'."}}